{
    "colleges": [
        {
            "img": "img/its.jpg?url",
            "link": "https://maps.app.goo.gl/bxV77jRjjS74CNm87"
        },
        {
            "img": "img/unair.jpg?url",
            "link": "https://maps.app.goo.gl/ppsMuhD9Y1MVbKbr5"
        },
        {
            "img": "img/ub.jpeg?url",
            "link": "https://maps.app.goo.gl/fzUv7GGuZ1Vq2SWF8"
        },
        {
            "img": "img/um.jpg?url",
            "link": "https://maps.app.goo.gl/G8D7QAFHBNG6qqsT6"
        },
        {
            "img": "img/polinema.jpg?url",
            "link": "https://maps.app.goo.gl/qrJ2TyQ5fRzpmzFQ9"
        },
        {
            "img": "img/unesa.jpg?url",
            "link": "https://maps.app.goo.gl/rFqKjQcyzKaCv5sG8"
        },
        {
            "img": "img/unej.jpg?url",
            "link": "https://maps.app.goo.gl/HPF52Vqn5P7yawP49"
        },
        
        {
            "img": "img/upn.jpg?url",
            "link": "https://maps.app.goo.gl/XWMFmaQurYkF8fNP9"
        },
        {
            "img": "img/uin.jpg?url",
            "link": "https://maps.app.goo.gl/3pXQydBYK6ririYJA"
        },
        {
            "img": "img/umm.jpeg?url",
            "link": "https://maps.app.goo.gl/6U95xud9suqrY9Ax7"
        },
        {
            "img": "img/pens.jpg?url",
            "link": "https://maps.app.goo.gl/LXeXFFGq1NidexYL6"
        }
    ]
}